<PAMDataset>
  <Metadata>
    <MDI key="DataType">Generic</MDI>
  </Metadata>
  <PAMRasterBand band="1">
    <Description>Band_1</Description>
    <Histograms>
      <HistItem>
        <HistMin>3.516666650772095</HistMin>
        <HistMax>29</HistMax>
        <BucketCount>256</BucketCount>
        <IncludeOutOfRange>1</IncludeOutOfRange>
        <Approximate>0</Approximate>
        <HistCounts>2|0|3|1|3|7|1|3|8|9|4|10|12|10|17|32|31|44|51|58|42|41|47|35|39|57|53|63|60|63|75|79|93|87|112|128|132|111|145|132|132|159|146|169|154|155|155|182|230|205|206|231|217|270|302|287|334|330|376|388|345|405|450|456|487|474|553|588|561|657|712|744|771|848|838|866|868|916|883|1000|1093|1168|1216|1303|1455|1558|1677|1803|1824|1997|2117|2088|2049|2257|2459|2655|2771|2652|2571|2420|2314|2341|2535|2492|2535|2677|2801|2861|2712|2776|2961|3249|3328|3383|3558|3978|4138|4200|4390|4610|4537|4612|4721|4957|5137|5302|5720|5841|5896|5992|6186|6510|6332|6296|6207|6397|6706|6898|7098|7264|7598|7799|8130|8684|8844|8868|9230|9626|10152|10326|10514|10975|11123|11008|11219|11649|11462|11792|11662|11631|11582|11960|12653|13155|12713|12311|12280|12310|12607|12067|11918|11822|11721|11853|11560|11204|10999|10656|10532|10666|10703|10793|10848|11136|11433|11511|11438|11585|11538|11526|11974|12427|11819|11707|11928|11297|11702|11494|11504|11557|11931|12428|13078|13193|12600|11825|11571|11963|11770|11828|11859|11385|11446|11315|10451|9798|9912|11031|12829|11926|11129|10274|10350|10063|8701|8508|8262|7952|7927|6815|6242|5938|6013|5961|6153|6076|5026|5149|4917|4537|4558|4408|4329|3726|3829|4184|4736|4226|3380|2879|2611|2024|1384|640|212|1</HistCounts>
      </HistItem>
    </Histograms>
    <Metadata>
      <MDI key="BandName">Band_1</MDI>
      <MDI key="RepresentationType">ATHEMATIC</MDI>
      <MDI key="STATISTICS_COVARIANCES">16.2445128484022</MDI>
      <MDI key="STATISTICS_EXCLUDEDVALUES"></MDI>
      <MDI key="STATISTICS_MAXIMUM">29</MDI>
      <MDI key="STATISTICS_MEAN">21.141764233033</MDI>
      <MDI key="STATISTICS_MINIMUM">3.5166666507721</MDI>
      <MDI key="STATISTICS_SKIPFACTORX">1</MDI>
      <MDI key="STATISTICS_SKIPFACTORY">1</MDI>
      <MDI key="STATISTICS_STDDEV">4.030448219293</MDI>
    </Metadata>
  </PAMRasterBand>
</PAMDataset>
